LICENSE
README.md
requirements.txt
NnSetting/Source.py
NnSetting/__init__.py
NnSetting.egg-info/PKG-INFO
NnSetting.egg-info/SOURCES.txt
NnSetting.egg-info/dependency_links.txt
NnSetting.egg-info/not-zip-safe
NnSetting.egg-info/requires.txt
NnSetting.egg-info/top_level.txt
test/test.py
NnSetting-1.0.0.dist-info/LICENSE
NnSetting-1.0.0.dist-info/METADATA
NnSetting-1.0.0.dist-info/WHEEL
NnSetting-1.0.0.dist-info/top_level.txt
NnSetting-1.0.0.dist-info/RECORD
