Metadata-Version: 2.1
Name: NnSetting
Version: 1.0.0
Summary: 一个通用型多环境设置管理工具
Home-page: https://github.com/OToNaShi-4/NnSetting
Author: OToNaShi-4
Author-email: 517431682@qq.com
License: UNKNOWN
Keywords: asyncio,aiomysql,orm
Platform: UNKNOWN
Classifier: Intended Audience :: Developers
Classifier: License :: OSI Approved :: MIT License
Classifier: Natural Language :: English
Classifier: Programming Language :: Python :: 3.7
Classifier: Programming Language :: Python :: 3.8
Classifier: Programming Language :: Python :: 3.10
Requires-Python: >=3.6.0
License-File: LICENSE
Requires-Dist: Faker (~=9.8.3)
Requires-Dist: astor (~=0.8.1)
Requires-Dist: setuptools (~=59.6.0)
Requires-Dist: Cython (~=0.29.24)
Requires-Dist: case-convert
Requires-Dist: wheel
